audata/__init__.py
audata/_utils.py
audata/dataset.py
audata/element.py
audata/file.py
audata/group.py
audata/_test/__init__.py
audata/_test/gendata.py
audata/_test/readwrite.py
audata/bin/__init__.py
audata/bin/csv2audata.py
audata-1.0.4.dist-info/LICENSE
audata-1.0.4.dist-info/METADATA
audata-1.0.4.dist-info/WHEEL
audata-1.0.4.dist-info/entry_points.txt
audata-1.0.4.dist-info/top_level.txt
audata-1.0.4.dist-info/RECORD
